{
  "best_model": "XGBoost",
  "rmse": 10.7503,
  "mae": 7.4658,
  "r2": 0.8794,
  "feature_cols": [
    "temp",
    "feels_like",
    "humidity",
    "pressure",
    "wind_speed",
    "wind_direction",
    "precipitation",
    "weather_code",
    "hour_sin",
    "hour_cos",
    "month_sin",
    "month_cos",
    "dayofweek",
    "is_weekend",
    "is_rush_hour",
    "season",
    "is_hot",
    "is_cold",
    "is_calm_wind",
    "is_strong_wind",
    "is_stagnant",
    "temp_humidity",
    "wind_humidity",
    "aqi_lag_72h",
    "aqi_lag_96h",
    "aqi_rolling_72h",
    "aqi_rolling_96h"
  ],
  "trained_at": "2026-05-24 06:41:10",
  "all_results": [
    {
      "model": "Random Forest",
      "rmse": 14.0582,
      "mae": 9.7933,
      "r2": 0.7938
    },
    {
      "model": "Gradient Boosting",
      "rmse": 12.1221,
      "mae": 7.9863,
      "r2": 0.8467
    },
    {
      "model": "XGBoost",
      "rmse": 10.7503,
      "mae": 7.4658,
      "r2": 0.8794
    },
    {
      "model": "Ridge Regression",
      "rmse": 83.4571,
      "mae": 37.8474,
      "r2": -6.2677
    }
  ]
}